Metadata-Version: 2.1
Name: glauber-video-ferramentas
Version: 1.0
Summary: Este pacote irá fornecer ferramentas de processamento de vídeo
Author: Glauber
Author-email: glaubercostaferreira@gmail.com
Keywords: camera,video,processamento
License-File: license.txt
